py_wslrun-0.1.2.data/scripts/wslrun_test
wslrun/__init__.py
wslrun/main.py
py_wslrun-0.1.2.dist-info/METADATA
py_wslrun-0.1.2.dist-info/WHEEL
py_wslrun-0.1.2.dist-info/entry_points.txt
py_wslrun-0.1.2.dist-info/top_level.txt
py_wslrun-0.1.2.dist-info/RECORD
