Metadata-Version: 2.1
Name: py-wslrun
Version: 0.1.2
Summary: Testing Framework powered by Windows Subsystem for Linux (WSL)
Home-page: https://git-central.openfunction.co/jmarhee/wslrun
Author: jmarhee
Author-email: jmarhee@interiorae.com
License: MIT
Platform: UNKNOWN
Requires-Dist: pyyaml
